__init__.py
argfmt.py
pysde.py
pysde2json-0.0.4.dist-info/METADATA
pysde2json-0.0.4.dist-info/WHEEL
pysde2json-0.0.4.dist-info/entry_points.txt
pysde2json-0.0.4.dist-info/top_level.txt
pysde2json-0.0.4.dist-info/RECORD
