Metadata-Version: 2.1
Name: pysde2json
Version: 0.0.4
Summary: A python tool for converting the EVE static data export to json files.
Home-page: http://github.com/colcrunch/pysde2json
Author: colcrunch
Author-email: colcrunch@fancypants.space
License: GPLv2
Project-URL: Bug Tracker, https://github.com/colcrunch/pysde2json/issues
Keywords: eve,eve online
Platform: UNKNOWN
Classifier: Programming Language :: Python
Classifier: Programming Language :: Python :: 3
Classifier: Programming Language :: Python :: 3.10
Requires-Python: >=3.10
Requires-Dist: requests
